{
  "tags": [
    {
      "name": "release",
      "version": "3.0.5223",
      "commit": "dcbc876",
      "upstream": "v3",
      "lastUpdated": "2021-04-03T06:30:48.599Z"
    },
    {
      "name": "testing",
      "version": "4.0.1333",
      "commit": "2708700",
      "upstream": "v4",
      "lastUpdated": "2021-04-11T21:56:52.387Z"
    },
    {
      "name": "nightly",
      "version": "",
      "commit": "",
      "upstream": "",
      "lastUpdated": ""
    }
  ],
  "pulls": 14254922,
  "stars": 10
}
